LICENSE
MANIFEST.in
README.rst
setup.py
JSON_Datetime.egg-info/PKG-INFO
JSON_Datetime.egg-info/SOURCES.txt
JSON_Datetime.egg-info/dependency_links.txt
JSON_Datetime.egg-info/requires.txt
JSON_Datetime.egg-info/top_level.txt
jsondatetime/__init__.py
jsondatetime/jsondatetime.py
jsondatetime/tests/__init__.py
jsondatetime/tests/test_jsondatetime.py