Metadata-Version: 1.1
Name: JSON-Datetime
Version: 0.0.6
Summary: Allows for proper decoding of datetime values contained in JSON streams
Home-page: http://github.com/nicolaiarocci/json-datetime
Author: Nicola Iarocci
Author-email: nicola@nicolaiarocci.com
License: ISC
Platform: any
Classifier: Development Status :: 4 - Beta
Classifier: Intended Audience :: Developers
Classifier: License :: OSI Approved :: ISC License (ISCL)
Classifier: Operating System :: OS Independent
Classifier: Programming Language :: Python :: 2.5
Classifier: Programming Language :: Python :: 2.6
Classifier: Programming Language :: Python :: 2.7
Classifier: Programming Language :: Python :: 3
Requires: simplejson
